colibricore.cpython-38-darwin.so
colibricore-2.5.9.dist-info/RECORD
colibricore-2.5.9.dist-info/LICENSE
colibricore-2.5.9.dist-info/AUTHORS
colibricore-2.5.9.dist-info/WHEEL
colibricore-2.5.9.dist-info/COPYING
colibricore-2.5.9.dist-info/top_level.txt
colibricore-2.5.9.dist-info/METADATA
