Metadata-Version: 2.1
Name: colibricore
Version: 2.5.9
Summary: Colibri Core is an NLP tool as well as a C++ and Python library (all included in this package) for working with basic linguistic constructions such as n-grams and skipgrams (i.e patterns with one or more gaps, either of fixed or dynamic size) in a quick and memory-efficient way. At the core is the tool ``colibri-patternmodeller`` which allows you to build, view, manipulate and query pattern models.
Author: Maarten van Gompel
Author-email: proycon@anaproy.nl
License: GPLv3
Keywords: nlp computational_linguistics frequency ngram skipgram pmi cooccurrence linguistics
Classifier: Development Status :: 5 - Production/Stable
Classifier: Topic :: Text Processing :: Linguistic
Classifier: Programming Language :: Cython
Classifier: Programming Language :: Python :: 3
Classifier: Operating System :: POSIX
Classifier: Intended Audience :: Developers
Classifier: Intended Audience :: Science/Research
Classifier: License :: OSI Approved :: GNU General Public License v3 (GPLv3)
License-File: LICENSE
License-File: COPYING
License-File: AUTHORS
